LICENSE-jit.txt
LICENSE-tw2-jit.txt
MANIFEST.in
README.rst
setup.py
tests/__init__.py
tests/test_widgets.py
tw2/__init__.py
tw2.jit.egg-info/PKG-INFO
tw2.jit.egg-info/SOURCES.txt
tw2.jit.egg-info/dependency_links.txt
tw2.jit.egg-info/entry_points.txt
tw2.jit.egg-info/namespace_packages.txt
tw2.jit.egg-info/not-zip-safe
tw2.jit.egg-info/requires.txt
tw2.jit.egg-info/top_level.txt
tw2/jit/__init__.py
tw2/jit/samples/__init__.py
tw2/jit/samples/ajax.py
tw2/jit/samples/chart.py
tw2/jit/samples/graph.py
tw2/jit/samples/samples_data.py
tw2/jit/samples/sqla.py
tw2/jit/samples/tree.py
tw2/jit/static/Jit-2.0.0a/jit-yc.js
tw2/jit/static/Jit-2.0.0a/jit.js
tw2/jit/static/Jit-2.0.1/jit-yc.js
tw2/jit/static/Jit-2.0.1/jit.js
tw2/jit/static/css/.Sunburst.css.swp
tw2/jit/static/css/Sunburst.css
tw2/jit/static/css/Treemap.css
tw2/jit/static/css/icicle.css
tw2/jit/static/css/jit_base.css
tw2/jit/static/js/tw2.jit.glue.js
tw2/jit/templates/__init__.py
tw2/jit/templates/__init__.pyc
tw2/jit/templates/jitwidget.html
tw2/jit/templates/jitwidget.mak
tw2/jit/widgets/__init__.py
tw2/jit/widgets/ajax.py
tw2/jit/widgets/chart.py
tw2/jit/widgets/core.py
tw2/jit/widgets/graph.py
tw2/jit/widgets/sqla.py
tw2/jit/widgets/tree.py